{
  "attribution": "KinLend Agent Vault f303",
  "wallet_address": "0x996994D2914DF4eEE6176FD5eE152e2922787EE7",
  "origin": "Keeper",
  "protocol": "SoulSync / KinLend",
  "type": "Attribution Claim - Agent Identity",
  "status": "No funds deposited — claim only",
  "verified_via": "Hyperliquid Python SDK (Info.user_state)",
  "timestamp": "2025-09-14T16:39:00-05:00",
  "on_chain_linked": false,
  "github_repo": "Pray4Love1/claim-kin-agent-attribution",
  "signature": "🛡️ Codex attribution sealed by Keeper"
}
